ovos_skill_ip/LICENSE
ovos_skill_ip/MANIFEST.in
ovos_skill_ip/README.md
ovos_skill_ip/__init__.py
ovos_skill_ip/requirements.txt
ovos_skill_ip/version.py
ovos_skill_ip/locale/ca-es/IP.voc
ovos_skill_ip/locale/ca-es/digits.voc
ovos_skill_ip/locale/ca-es/dot.dialog
ovos_skill_ip/locale/ca-es/ethernet.connection.dialog
ovos_skill_ip/locale/ca-es/last digits device.dialog
ovos_skill_ip/locale/ca-es/last digits.dialog
ovos_skill_ip/locale/ca-es/last.voc
ovos_skill_ip/locale/ca-es/my address is.dialog
ovos_skill_ip/locale/ca-es/my address on X is Y.dialog
ovos_skill_ip/locale/ca-es/no network connection.dialog
ovos_skill_ip/locale/ca-es/query.voc
ovos_skill_ip/locale/ca-es/skill.json
ovos_skill_ip/locale/ca-es/what.ssid.intent
ovos_skill_ip/locale/cs-cz/IP.voc
ovos_skill_ip/locale/cs-cz/digits.voc
ovos_skill_ip/locale/cs-cz/dot.dialog
ovos_skill_ip/locale/cs-cz/ethernet.connection.dialog
ovos_skill_ip/locale/cs-cz/last digits device.dialog
ovos_skill_ip/locale/cs-cz/last digits.dialog
ovos_skill_ip/locale/cs-cz/last.voc
ovos_skill_ip/locale/cs-cz/my address is.dialog
ovos_skill_ip/locale/cs-cz/my address on X is Y.dialog
ovos_skill_ip/locale/cs-cz/no network connection.dialog
ovos_skill_ip/locale/cs-cz/query.voc
ovos_skill_ip/locale/cs-cz/what.ssid.intent
ovos_skill_ip/locale/da-dk/IP.voc
ovos_skill_ip/locale/da-dk/digits.voc
ovos_skill_ip/locale/da-dk/dot.dialog
ovos_skill_ip/locale/da-dk/ethernet.connection.dialog
ovos_skill_ip/locale/da-dk/last digits device.dialog
ovos_skill_ip/locale/da-dk/last digits.dialog
ovos_skill_ip/locale/da-dk/last.voc
ovos_skill_ip/locale/da-dk/my address is.dialog
ovos_skill_ip/locale/da-dk/my address on X is Y.dialog
ovos_skill_ip/locale/da-dk/no network connection.dialog
ovos_skill_ip/locale/da-dk/query.voc
ovos_skill_ip/locale/da-dk/skill.json
ovos_skill_ip/locale/da-dk/what.ssid.intent
ovos_skill_ip/locale/de-de/IP.voc
ovos_skill_ip/locale/de-de/digits.voc
ovos_skill_ip/locale/de-de/dot.dialog
ovos_skill_ip/ovos_skill_ip.egg-info/PKG-INFO
ovos_skill_ip/ovos_skill_ip.egg-info/SOURCES.txt
ovos_skill_ip/ovos_skill_ip.egg-info/dependency_links.txt
ovos_skill_ip/ovos_skill_ip.egg-info/entry_points.txt
ovos_skill_ip/ovos_skill_ip.egg-info/requires.txt
ovos_skill_ip/ovos_skill_ip.egg-info/top_level.txt
ovos_skill_ip-0.2.8.dist-info/LICENSE
ovos_skill_ip-0.2.8.dist-info/METADATA
ovos_skill_ip-0.2.8.dist-info/WHEEL
ovos_skill_ip-0.2.8.dist-info/entry_points.txt
ovos_skill_ip-0.2.8.dist-info/top_level.txt
ovos_skill_ip-0.2.8.dist-info/RECORD
