Metadata-Version: 2.1
Name: ovos-skill-ip
Version: 0.2.8
Summary: IPSkill
Home-page: https://github.com/OpenVoiceOS/ovos-skill-ip
Author: OpenVoiceOS
Author-email: 
License: Apache2.0
Keywords: ovos skill plugin
License-File: LICENSE
Requires-Dist: ifaddr
Requires-Dist: ovos-workshop
